README.txt
setup.cfg
setup.py
collective/__init__.py
collective.portlet.map.egg-info/PKG-INFO
collective.portlet.map.egg-info/SOURCES.txt
collective.portlet.map.egg-info/dependency_links.txt
collective.portlet.map.egg-info/entry_points.txt
collective.portlet.map.egg-info/namespace_packages.txt
collective.portlet.map.egg-info/not-zip-safe
collective.portlet.map.egg-info/paster_plugins.txt
collective.portlet.map.egg-info/requires.txt
collective.portlet.map.egg-info/top_level.txt
collective/portlet/__init__.py
collective/portlet/map/__init__.py
collective/portlet/map/configure.zcml
collective/portlet/map/mapportlet.pt
collective/portlet/map/mapportlet.py
collective/portlet/map/maps_override.py
collective/portlet/map/overrides.zcml
collective/portlet/map/version.txt
collective/portlet/map/locales/collective.portlet.map.pot
collective/portlet/map/locales/en/LC_MESSAGES/collective.portlet.map.po
collective/portlet/map/locales/it/LC_MESSAGES/collective.portlet.map.po
collective/portlet/map/profiles/default/metadata.xml
collective/portlet/map/profiles/default/portlets.xml
collective/portlet/map/tests/__init__.py
collective/portlet/map/tests/base.py
collective/portlet/map/tests/test_portlet.py
docs/HISTORY.txt
docs/INSTALL.txt
docs/LICENSE.GPL
docs/LICENSE.txt