Metadata-Version: 1.0
Name: collective.portlet.map
Version: 1.0dev-r75856
Summary: Google Map portlet
Home-page: http://www.reflab.it
Author: Riccardo Lemmi
Author-email: riccardo@reflab.it
License: GPL
Platform: UNKNOWN
Classifier: Framework :: Plone
Classifier: Programming Language :: Python
Classifier: Topic :: Software Development :: Libraries :: Python Modules
